refnx/__init__.py
refnx/conftest.py
refnx/version.py
refnx/_lib/__init__.py
refnx/_lib/_cutil.cpython-311-x86_64-linux-gnu.so
refnx/_lib/_numdiff.py
refnx/_lib/_pymc.py
refnx/_lib/_testutils.py
refnx/_lib/util.py
refnx/_lib/emcee/LICENSE
refnx/_lib/emcee/__init__.py
refnx/_lib/emcee/autocorr.py
refnx/_lib/emcee/ensemble.py
refnx/_lib/emcee/interruptible_pool.py
refnx/_lib/emcee/model.py
refnx/_lib/emcee/mpi_pool.py
refnx/_lib/emcee/pbar.py
refnx/_lib/emcee/ptsampler.py
refnx/_lib/emcee/state.py
refnx/_lib/emcee/utils.py
refnx/_lib/emcee/backends/__init__.py
refnx/_lib/emcee/backends/backend.py
refnx/_lib/emcee/backends/hdf.py
refnx/_lib/emcee/moves/__init__.py
refnx/_lib/emcee/moves/de.py
refnx/_lib/emcee/moves/de_snooker.py
refnx/_lib/emcee/moves/gaussian.py
refnx/_lib/emcee/moves/kde.py
refnx/_lib/emcee/moves/mh.py
refnx/_lib/emcee/moves/move.py
refnx/_lib/emcee/moves/red_blue.py
refnx/_lib/emcee/moves/stretch.py
refnx/_lib/emcee/moves/walk.py
refnx/_lib/ptemcee/LICENSE
refnx/_lib/ptemcee/__init__.py
refnx/_lib/ptemcee/chain.py
refnx/_lib/ptemcee/ensemble.py
refnx/_lib/ptemcee/interruptible_pool.py
refnx/_lib/ptemcee/mpi_pool.py
refnx/_lib/ptemcee/sampler.py
refnx/_lib/ptemcee/tests.py
refnx/_lib/ptemcee/util.py
refnx/_lib/tests/__init__.py
refnx/_lib/tests/test_import.py
refnx/_lib/tests/test_util.py
refnx/analysis/__init__.py
refnx/analysis/bounds.py
refnx/analysis/curvefitter.py
refnx/analysis/model.py
refnx/analysis/objective.py
refnx/analysis/parameter.py
refnx/analysis/tests/NISTModels.py
refnx/analysis/tests/__init__.py
refnx/analysis/tests/c_PLP0011859_q.txt
refnx/analysis/tests/c_PLP0016596.dat
refnx/analysis/tests/c_PLP0016601.dat
refnx/analysis/tests/c_PLP0016607.dat
refnx/analysis/tests/e361r.txt
refnx/analysis/tests/e365r.txt
refnx/analysis/tests/e366r.txt
refnx/analysis/tests/gauss_data.txt
refnx/analysis/tests/resolution_comparison.ipynb
refnx/analysis/tests/test_bounds.py
refnx-0.1.61.dist-info/METADATA
refnx-0.1.61.dist-info/WHEEL
refnx-0.1.61.dist-info/entry_points.txt
refnx-0.1.61.dist-info/top_level.txt
refnx-0.1.61.dist-info/RECORD
refnx-0.1.61.dist-info/licenses/LICENSE
